typhoon/CHANGELOG
typhoon/COPYING.LESSER
typhoon/LICENSE
typhoon/README
typhoon/__init__.py
typhoon/api/__init__.py
typhoon/api/constants.py
typhoon/api/utils.py
typhoon/api/version.py
typhoon/api/common/__init__.py
typhoon/api/common/data_frame_serialization.py
typhoon/api/configuration/__init__.py
typhoon/api/configuration/exception.py
typhoon/api/configuration/schema.py
typhoon/api/configuration/stub.py
typhoon/api/device_manager/__init__.py
typhoon/api/device_manager/exceptions.py
typhoon/api/device_manager/stub.py
typhoon/api/hil/__init__.py
typhoon/api/hil/exception.py
typhoon/api/hil/handle.py
typhoon/api/hil/stub.py
typhoon/api/iec_61850/__init__.py
typhoon/api/iec_61850/exceptions.py
typhoon/api/iec_61850/mms_utils.py
typhoon/api/iec_61869/__init__.py
typhoon/api/iec_61869/exceptions.py
typhoon/api/iec_61869/sv_utils.py
typhoon/api/modbus/__init__.py
typhoon/api/modbus/const.py
typhoon/api/modbus/exceptions.py
typhoon/api/modbus/util.py
typhoon/api/modbus/lang/__init__.py
typhoon/api/package_manager/__init__.py
typhoon/api/package_manager/base.py
typhoon/api/package_manager/const.py
typhoon/api/package_manager/exception.py
typhoon/api/package_manager/package.py
typhoon/api/package_manager/stub.py
typhoon/api/pv_generator/__init__.py
typhoon/api/pv_generator/stub.py
typhoon/api/scada/__init__.py
typhoon/api/scada/const.py
typhoon/api/scada/exception.py
typhoon/api/scada/handle.py
typhoon/api/scada/stub.py
typhoon/api/schematic_editor/__init__.py
typhoon/api/schematic_editor/const.py
typhoon/api/schematic_editor/exception.py
typhoon/api/schematic_editor/handle.py
typhoon/api/schematic_editor/stub.py
typhoon_hil_api-1.31.1.dist-info/METADATA
typhoon_hil_api-1.31.1.dist-info/WHEEL
typhoon_hil_api-1.31.1.dist-info/top_level.txt
typhoon_hil_api-1.31.1.dist-info/RECORD
