Metadata-Version: 2.4
Name: Typhoon-HIL-API
Version: 1.31.1
Summary: Typhoon HIL Application Programming Interface library
Author: Typhoon HIL, Inc
License: LGPL-3.0-only
Classifier: Topic :: Software Development
Classifier: Intended Audience :: Developers
Classifier: Topic :: Software Development :: Libraries :: Python Modules
Classifier: License :: OSI Approved :: GNU Lesser General Public License v3 (LGPLv3)
Classifier: Programming Language :: Python
Requires-Python: >=3.8
Requires-Dist: jinja2
Requires-Dist: pyarrow
Requires-Dist: pyModbusTCP
Requires-Dist: backports.functools_lru_cache
Requires-Dist: textx==4.1.0; python_version == "3.11"
Requires-Dist: textx==3.1.1; python_version < "3.11"
Requires-Dist: numpy<2,>=1.23.1; python_version < "3.11"
Requires-Dist: numpy==2.2.3; python_version == "3.11"
Requires-Dist: pyzmq>=26.2.1
Requires-Dist: pandas>=2.1.4; python_version > "3.8" and python_version < "3.12"
Requires-Dist: pandas==2.2.3; python_version == "3.11"
Requires-Dist: pandas<=2.0.3; python_version == "3.8"
Requires-Dist: win-inet-pton; platform_system == "Windows"
